up_esb/__init__.py
up_esb/bridge.py
up_esb/exceptions.py
up_esb/logger.py
up_esb/status.py
up_esb/components/__init__.py
up_esb/components/actions.py
up_esb/components/expression_manager.py
up_esb/components/graph.py
up_esb/execution/__init__.py
up_esb/execution/executor.py
up_esb/execution/parallel_executor.py
up_esb/plexmo/__init__.py
up_esb/plexmo/dispatcher.py
up_esb/plexmo/monitor.py
up_esb-0.1.20.dist-info/licenses/LICENSE
up_esb-0.1.20.dist-info/METADATA
up_esb-0.1.20.dist-info/WHEEL
up_esb-0.1.20.dist-info/top_level.txt
up_esb-0.1.20.dist-info/RECORD
