Metadata-Version: 2.4
Name: up_esb
Version: 0.1.20
Summary: General functionalities for using unified-planning in robotic applications
License: Apache-2.0 License
Project-URL: Homepage, https://www.aiplan4eu-project.eu/
Project-URL: Repository, https://github.com/aiplan4eu/embedded-systems-bridge
Keywords: unified-planning,embedded-systems-bridge
Classifier: Programming Language :: Python :: 3
Requires-Python: >=3.8
License-File: LICENSE
Requires-Dist: unified-planning>=1.0.0
Requires-Dist: networkx
Requires-Dist: matplotlib
Provides-Extra: dev
Requires-Dist: black; extra == "dev"
Requires-Dist: mypy; extra == "dev"
Requires-Dist: ruff; extra == "dev"
Requires-Dist: pytest; extra == "dev"
Requires-Dist: pre-commit; extra == "dev"
Provides-Extra: engines
Requires-Dist: up-aries; extra == "engines"
Requires-Dist: up-pyperplan; extra == "engines"
Dynamic: license-file
